im_task_webapp2/__init__.py
im_task_webapp2-0.1.0.dist-info/DESCRIPTION.rst
im_task_webapp2-0.1.0.dist-info/METADATA
im_task_webapp2-0.1.0.dist-info/RECORD
im_task_webapp2-0.1.0.dist-info/WHEEL
im_task_webapp2-0.1.0.dist-info/metadata.json
im_task_webapp2-0.1.0.dist-info/top_level.txt
